[{"ID":7500,"Offset":4032,"Name":"蛟蜥精准手套","Description":null},{"ID":7501,"Offset":4240,"Name":"羊绒精准短裙","Description":null},{"ID":7502,"Offset":4448,"Name":"蛟蜥精准筒靴","Description":null},{"ID":7503,"Offset":4656,"Name":"蛟蜥精准腰带","Description":null},{"ID":7504,"Offset":4864,"Name":"黄金眼镜","Description":null},{"ID":7505,"Offset":5060,"Name":"羊绒治愈长袍","Description":null},{"ID":7506,"Offset":5268,"Name":"蛟蜥治愈手套","Description":null},{"ID":7507,"Offset":5476,"Name":"羊绒治愈短裙","Description":null},{"ID":7508,"Offset":5684,"Name":"蛟蜥治愈长靴","Description":null},{"ID":7509,"Offset":5892,"Name":"蛟蜥治愈腰带","Description":null},{"ID":7510,"Offset":6100,"Name":"羊绒咏咒宽边帽","Description":null},{"ID":7511,"Offset":6312,"Name":"羊绒咏咒长袍","Description":null},{"ID":7512,"Offset":6520,"Name":"蛟蜥咏咒手套","Description":null},{"ID":7513,"Offset":6728,"Name":"羊绒咏咒马裤","Description":null},{"ID":7514,"Offset":6936,"Name":"蛟蜥咏咒尖头靴","Description":null},{"ID":7515,"Offset":7148,"Name":"蛟蜥咏咒腰带","Description":null},{"ID":7516,"Offset":7356,"Name":"御敌缎带","Description":null},{"ID":7517,"Offset":7552,"Name":"强攻缎带","Description":null},{"ID":7518,"Offset":7748,"Name":"精准缎带","Description":null},{"ID":7519,"Offset":7944,"Name":"咏咒缎带","Description":null},{"ID":7520,"Offset":8140,"Name":"治愈缎带","Description":null},{"ID":7521,"Offset":8336,"Name":"工匠下框眼镜","Description":null},{"ID":7522,"Offset":8544,"Name":"征粮草帽","Description":null},{"ID":7523,"Offset":8740,"Name":"工匠陆行鸟手锯","Description":null},{"ID":7524,"Offset":8952,"Name":"工匠横头锤","Description":null},{"ID":7525,"Offset":9152,"Name":"工匠圆头锤","Description":null},{"ID":7526,"Offset":9352,"Name":"工匠雕金锤","Description":null},{"ID":7527,"Offset":9552,"Name":"工匠圆革刀","Description":null},{"ID":7528,"Offset":9752,"Name":"工匠缝针","Description":null},{"ID":7529,"Offset":9948,"Name":"工匠蒸馏器","Description":null},{"ID":7530,"Offset":10148,"Name":"工匠平底锅","Description":null},{"ID":7531,"Offset":10348,"Name":"征粮鹤嘴镐","Description":null},{"ID":7532,"Offset":10548,"Name":"征粮手斧","Description":null},{"ID":7533,"Offset":10744,"Name":"征粮钓竿","Description":null},{"ID":7534,"Offset":10940,"Name":"盛花草帽","Description":null},{"ID":7535,"Offset":11136,"Name":"水手服","Description":null},{"ID":7536,"Offset":11324,"Name":"盛花腕带","Description":null},{"ID":7537,"Offset":11520,"Name":"水手裤","Description":null},{"ID":7538,"Offset":11708,"Name":"水手甲板鞋","Description":null},{"ID":7539,"Offset":11908,"Name":"春意草帽","Description":null},{"ID":7540,"Offset":12116,"Name":"春意礼服","Description":null},{"ID":7541,"Offset":12324,"Name":"春意长裙","Description":null},{"ID":7542,"Offset":12532,"Name":"春意礼鞋","Description":null},{"ID":7543,"Offset":12740,"Name":"花草帽","Description":null},{"ID":7544,"Offset":12928,"Name":"魔石精兜帽","Description":null},{"ID":7545,"Offset":13128,"Name":"哥布林兜帽","Description":null},{"ID":7546,"Offset":13328,"Name":"轻钢肩甲","Description":null},{"ID":7547,"Offset":13524,"Name":"轻钢三角裤","Description":null},{"ID":7548,"Offset":13724,"Name":"平纹披肩","Description":null},{"ID":7549,"Offset":13920,"Name":"平纹腰布裙","Description":null},{"ID":7550,"Offset":14120,"Name":"猎蛋装甲","Description":null},{"ID":7551,"Offset":14360,"Name":"光之鸟甲","Description":null},{"ID":7552,"Offset":14624,"Name":"利维亚桑装甲","Description":null},{"ID":7553,"Offset":14896,"Name":"胖陆行鸟笛","Description":null},{"ID":7554,"Offset":15152,"Name":"水龙蜥角笛","Description":null},{"ID":7555,"Offset":15408,"Name":"爆弹角笛","Description":null},{"ID":7556,"Offset":15656,"Name":"地灵娃娃","Description":null},{"ID":7557,"Offset":15944,"Name":"鱼人玩偶","Description":null},{"ID":7558,"Offset":16244,"Name":"莫古力娃娃","Description":null},{"ID":7559,"Offset":16520,"Name":"软软垫子","Description":null},{"ID":7560,"Offset":16816,"Name":"发条太阳","Description":null},{"ID":7561,"Offset":17180,"Name":"奥丁战偶","Description":null},{"ID":7562,"Offset":17500,"Name":"光之战士","Description":null},{"ID":7563,"Offset":17756,"Name":"发条巴哈姆特","Description":null},{"ID":7564,"Offset":18088,"Name":"奥猴宝宝","Description":null},{"ID":7565,"Offset":18356,"Name":"","Description":null},{"ID":7566,"Offset":18528,"Name":"夺心小魔","Description":null},{"ID":7567,"Offset":18816,"Name":"","Description":null},{"ID":7568,"Offset":18988,"Name":"魔法扫帚","Description":null},{"ID":7569,"Offset":19288,"Name":"传送网使用券","Description":null},{"ID":7570,"Offset":19584,"Name":"酒香蒸鲶鱼","Description":null},{"ID":7571,"Offset":19892,"Name":"新薯煎饼","Description":null},{"ID":7572,"Offset":20204,"Name":"香烤填鸭","Description":null},{"ID":7573,"Offset":20520,"Name":"萨赫蛋糕","Description":null},{"ID":7574,"Offset":20812,"Name":"新薯冷汤","Description":null},{"ID":7575,"Offset":21120,"Name":"菠菜乳蛋饼","Description":null},{"ID":7576,"Offset":21460,"Name":"","Description":null},{"ID":7577,"Offset":21632,"Name":"亚拉戈时光沙","Description":null},{"ID":7578,"Offset":21940,"Name":"亚拉戈时光油","Description":null},{"ID":7579,"Offset":22248,"Name":"长满苔藓的石剑","Description":null},{"ID":7580,"Offset":22552,"Name":"长满苔藓的石斧","Description":null},{"ID":7581,"Offset":22856,"Name":"长满苔藓的石爪","Description":null},{"ID":7582,"Offset":23160,"Name":"长满苔藓的石枪","Description":null},{"ID":7583,"Offset":23464,"Name":"长满苔藓的石弓","Description":null},{"ID":7584,"Offset":23768,"Name":"长满苔藓的石杖","Description":null},{"ID":7585,"Offset":24072,"Name":"长满苔藓的石棒","Description":null},{"ID":7586,"Offset":24376,"Name":"褪色的古书","Description":null},{"ID":7587,"Offset":24644,"Name":"褪色的古典","Description":null},{"ID":7588,"Offset":24912,"Name":"钨铁矿","Description":null},{"ID":7589,"Offset":25136,"Name":"自然金","Description":null},{"ID":7590,"Offset":25356,"Name":"绯红树汁","Description":null},{"ID":7591,"Offset":25604,"Name":"提诺尔卡茶叶","Description":null},{"ID":7592,"Offset":25888,"Name":"黄杏","Description":null},{"ID":7593,"Offset":26192,"Name":"拉诺西亚韭菜","Description":null},{"ID":7594,"Offset":26488,"Name":"谢尔达莱嫩菠菜","Description":null},{"ID":7595,"Offset":26796,"Name":"鲜血橙","Description":null},{"ID":7596,"Offset":27116,"Name":"硅化木","Description":null},{"ID":7597,"Offset":27348,"Name":"白钨矿","Description":null},{"ID":7598,"Offset":27584,"Name":"拉吉克灵沙","Description":null},{"ID":7599,"Offset":27868,"Name":"蛟蜥的粗皮","Description":null},{"ID":7600,"Offset":28104,"Name":"山羊绒","Description":null},{"ID":7601,"Offset":28328,"Name":"金刚砂","Description":null},{"ID":7602,"Offset":28560,"Name":"星八角","Description":null},{"ID":7603,"Offset":28820,"Name":"卫月新薯","Description":null},{"ID":7604,"Offset":29116,"Name":"皇家可可豆","Description":null},{"ID":7605,"Offset":29408,"Name":"填鸭胸肉","Description":null},{"ID":7606,"Offset":29656,"Name":"古神木材","Description":null},{"ID":7607,"Offset":29880,"Name":"钨钢锭","Description":null},{"ID":7608,"Offset":30140,"Name":"蛟蜥革","Description":null},{"ID":7609,"Offset":30356,"Name":"羊绒布","Description":null},{"ID":7610,"Offset":30580,"Name":"灵性岩","Description":null},{"ID":7611,"Offset":30796,"Name":"黑衣香木","Description":null},{"ID":7612,"Offset":31048,"Name":"云杉合板","Description":null},{"ID":7613,"Offset":31296,"Name":"玄钢钩","Description":null},{"ID":7614,"Offset":31520,"Name":"玄钢丝","Description":null},{"ID":7615,"Offset":31744,"Name":"玫瑰金齿轮","Description":null},{"ID":7616,"Offset":31980,"Name":"骏鹰革细绳","Description":null},{"ID":7617,"Offset":32216,"Name":"银丝织锦","Description":null},{"ID":7618,"Offset":32452,"Name":"盐酸","Description":null},{"ID":7619,"Offset":32672,"Name":"番茄酱","Description":null},{"ID":7620,"Offset":32940,"Name":"稀硫酸","Description":null},{"ID":7621,"Offset":33160,"Name":"驱幻晶","Description":null},{"ID":7622,"Offset":33464,"Name":"1级木工幻象棱晶","Description":null},{"ID":7623,"Offset":33860,"Name":"2级木工幻象棱晶","Description":null},{"ID":7624,"Offset":34256,"Name":"3级木工幻象棱晶","Description":null},{"ID":7625,"Offset":34652,"Name":"4级木工幻象棱晶","Description":null},{"ID":7626,"Offset":35048,"Name":"5级木工幻象棱晶","Description":null},{"ID":7627,"Offset":35444,"Name":"","Description":null},{"ID":7628,"Offset":35616,"Name":"","Description":null},{"ID":7629,"Offset":35788,"Name":"1级锻冶幻象棱晶","Description":null},{"ID":7630,"Offset":36184,"Name":"2级锻冶幻象棱晶","Description":null},{"ID":7631,"Offset":36580,"Name":"3级锻冶幻象棱晶","Description":null},{"ID":7632,"Offset":36976,"Name":"4级锻冶幻象棱晶","Description":null},{"ID":7633,"Offset":37372,"Name":"5级锻冶幻象棱晶","Description":null},{"ID":7634,"Offset":37768,"Name":"","Description":null},{"ID":7635,"Offset":37940,"Name":"","Description":null},{"ID":7636,"Offset":38112,"Name":"1级甲胄幻象棱晶","Description":null},{"ID":7637,"Offset":38508,"Name":"2级甲胄幻象棱晶","Description":null},{"ID":7638,"Offset":38904,"Name":"3级甲胄幻象棱晶","Description":null},{"ID":7639,"Offset":39300,"Name":"4级甲胄幻象棱晶","Description":null},{"ID":7640,"Offset":39696,"Name":"5级甲胄幻象棱晶","Description":null},{"ID":7641,"Offset":40092,"Name":"","Description":null},{"ID":7642,"Offset":40264,"Name":"","Description":null},{"ID":7643,"Offset":40436,"Name":"1级雕金幻象棱晶","Description":null},{"ID":7644,"Offset":40832,"Name":"2级雕金幻象棱晶","Description":null},{"ID":7645,"Offset":41228,"Name":"3级雕金幻象棱晶","Description":null},{"ID":7646,"Offset":41624,"Name":"4级雕金幻象棱晶","Description":null},{"ID":7647,"Offset":42020,"Name":"5级雕金幻象棱晶","Description":null},{"ID":7648,"Offset":42416,"Name":"","Description":null},{"ID":7649,"Offset":42588,"Name":"","Description":null},{"ID":7650,"Offset":42760,"Name":"1级皮革幻象棱晶","Description":null},{"ID":7651,"Offset":43156,"Name":"2级皮革幻象棱晶","Description":null},{"ID":7652,"Offset":43552,"Name":"3级皮革幻象棱晶","Description":null},{"ID":7653,"Offset":43948,"Name":"4级皮革幻象棱晶","Description":null},{"ID":7654,"Offset":44344,"Name":"5级皮革幻象棱晶","Description":null},{"ID":7655,"Offset":44740,"Name":"","Description":null},{"ID":7656,"Offset":44912,"Name":"","Description":null},{"ID":7657,"Offset":45084,"Name":"1级裁缝幻象棱晶","Description":null},{"ID":7658,"Offset":45480,"Name":"2级裁缝幻象棱晶","Description":null},{"ID":7659,"Offset":45876,"Name":"3级裁缝幻象棱晶","Description":null},{"ID":7660,"Offset":46272,"Name":"4级裁缝幻象棱晶","Description":null},{"ID":7661,"Offset":46668,"Name":"5级裁缝幻象棱晶","Description":null},{"ID":7662,"Offset":47064,"Name":"","Description":null},{"ID":7663,"Offset":47236,"Name":"","Description":null},{"ID":7664,"Offset":47408,"Name":"1级炼金幻象棱晶","Description":null},{"ID":7665,"Offset":47804,"Name":"2级炼金幻象棱晶","Description":null},{"ID":7666,"Offset":48204,"Name":"3级炼金幻象棱晶","Description":null},{"ID":7667,"Offset":48604,"Name":"4级炼金幻象棱晶","Description":null},{"ID":7668,"Offset":49004,"Name":"5级炼金幻象棱晶","Description":null},{"ID":7669,"Offset":49404,"Name":"","Description":null},{"ID":7670,"Offset":49576,"Name":"","Description":null},{"ID":7671,"Offset":49748,"Name":"1级纯净棱晶","Description":null},{"ID":7672,"Offset":49992,"Name":"2级纯净棱晶","Description":null},{"ID":7673,"Offset":50236,"Name":"3级纯净棱晶","Description":null},{"ID":7674,"Offset":50480,"Name":"4级纯净棱晶","Description":null},{"ID":7675,"Offset":50724,"Name":"5级纯净棱晶","Description":null},{"ID":7676,"Offset":50968,"Name":"","Description":null},{"ID":7677,"Offset":51140,"Name":"","Description":null},{"ID":7678,"Offset":51312,"Name":"扎尔艾拉","Description":null},{"ID":7679,"Offset":51560,"Name":"无赖王","Description":null},{"ID":7680,"Offset":51792,"Name":"山神印","Description":null},{"ID":7681,"Offset":52040,"Name":"高声鲶鱼","Description":null},{"ID":7682,"Offset":52280,"Name":"水晶刺鱼","Description":null},{"ID":7683,"Offset":52524,"Name":"莫尔巴","Description":null},{"ID":7684,"Offset":52760,"Name":"拾荒鮟鱇","Description":null},{"ID":7685,"Offset":53008,"Name":"金鳍蝶","Description":null},{"ID":7686,"Offset":53264,"Name":"巨鲨","Description":null},{"ID":7687,"Offset":53496,"Name":"鳞脚贝","Description":null},{"ID":7688,"Offset":53748,"Name":"隐沙鱼","Description":null},{"ID":7689,"Offset":53984,"Name":"暗骑士","Description":null},{"ID":7690,"Offset":54212,"Name":"银君","Description":null},{"ID":7691,"Offset":54472,"Name":"剑齿鳕","Description":null},{"ID":7692,"Offset":54708,"Name":"梦幻虾虎","Description":null},{"ID":7693,"Offset":54956,"Name":"海神剑","Description":null},{"ID":7694,"Offset":55196,"Name":"暗兵鳢","Description":null},{"ID":7695,"Offset":55432,"Name":"审判鳐","Description":null},{"ID":7696,"Offset":55680,"Name":"酿血鱼","Description":null},{"ID":7697,"Offset":55928,"Name":"仙后鲈","Description":null},{"ID":7698,"Offset":56164,"Name":"滑溜帝王","Description":null},{"ID":7699,"Offset":56412,"Name":"蓝寡妇","Description":null},{"ID":7700,"Offset":56648,"Name":"人面鲤","Description":null},{"ID":7701,"Offset":56880,"Name":"倔强鲫鱼","Description":null},{"ID":7702,"Offset":57132,"Name":"朝圣泥鱼","Description":null},{"ID":7703,"Offset":57376,"Name":"垂暮蝲蛄","Description":null},{"ID":7704,"Offset":57620,"Name":"净髓蜗牛","Description":null},{"ID":7705,"Offset":57868,"Name":"外科医生","Description":null},{"ID":7706,"Offset":58116,"Name":"泥巨蟹兵","Description":null},{"ID":7707,"Offset":58356,"Name":"猛犸章鱼","Description":null},{"ID":7708,"Offset":58620,"Name":"圣母鲤","Description":null},{"ID":7709,"Offset":58856,"Name":"高刺鱼","Description":null},{"ID":7710,"Offset":59100,"Name":"希尔德拉","Description":null},{"ID":7711,"Offset":59348,"Name":"铆钉牡蛎","Description":null},{"ID":7712,"Offset":59596,"Name":"剪刀手雅克","Description":null},{"ID":7713,"Offset":59852,"Name":"招雨王","Description":null},{"ID":7714,"Offset":60088,"Name":"铜镜","Description":null},{"ID":7715,"Offset":60316,"Name":"红辣椒种子","Description":null},{"ID":7716,"Offset":60548,"Name":"野洋葱球根","Description":null},{"ID":7717,"Offset":60780,"Name":"库尔札斯胡萝卜种子","Description":null},{"ID":7718,"Offset":61048,"Name":"拉诺西亚莴苣种子","Description":null},{"ID":7719,"Offset":61308,"Name":"橄榄种子","Description":null},{"ID":7720,"Offset":61532,"Name":"新薯芽块","Description":null},{"ID":7721,"Offset":61756,"Name":"多实玉米种子","Description":null},{"ID":7722,"Offset":61996,"Name":"巫茄种子","Description":null},{"ID":7723,"Offset":62220,"Name":"中原甘蓝种子","Description":null},{"ID":7724,"Offset":62460,"Name":"泽梅尔番茄种子","Description":null},{"ID":7725,"Offset":62708,"Name":"拉诺西亚香橙种子","Description":null},{"ID":7726,"Offset":62968,"Name":"低地葡萄种子","Description":null},{"ID":7727,"Offset":63208,"Name":"仙女苹果种子","Description":null},{"ID":7728,"Offset":63448,"Name":"太阳柠檬种子","Description":null},{"ID":7729,"Offset":63688,"Name":"仙子梅种子","Description":null},{"ID":7730,"Offset":63920,"Name":"血红奇异果种子","Description":null},{"ID":7731,"Offset":64168,"Name":"晶亮苹果种子","Description":null},{"ID":7732,"Offset":64408,"Name":"罗兰莓种子","Description":null},{"ID":7733,"Offset":64640,"Name":"蜜柠檬种子","Description":null},{"ID":7734,"Offset":64872,"Name":"多刺菠萝种子","Description":null},{"ID":7735,"Offset":65112,"Name":"大蒜球根","Description":null},{"ID":7736,"Offset":65336,"Name":"薰衣草种子","Description":null},{"ID":7737,"Offset":65568,"Name":"黑胡椒种子","Description":null},{"ID":7738,"Offset":65800,"Name":"阿拉米格芥末种子","Description":null},{"ID":7739,"Offset":66060,"Name":"生姜根","Description":null},{"ID":7740,"Offset":66272,"Name":"甘菊种子","Description":null},{"ID":7741,"Offset":66496,"Name":"亚麻种子","Description":null},{"ID":7742,"Offset":66720,"Name":"中原罗勒草种子","Description":null},{"ID":7743,"Offset":66968,"Name":"风茄种子","Description":null},{"ID":7744,"Offset":67192,"Name":"扁桃种子","Description":null},{"ID":7745,"Offset":67416,"Name":"哈罗妮丁菊种子","Description":null},{"ID":7746,"Offset":67664,"Name":"阿泽玛玫瑰种子","Description":null},{"ID":7747,"Offset":67912,"Name":"妮美雅百合种子","Description":null},{"ID":7748,"Offset":68160,"Name":"星八角种子","Description":null},{"ID":7749,"Offset":68392,"Name":"卫月新薯芽块","Description":null},{"ID":7750,"Offset":68632,"Name":"皇家可可豆种子","Description":null},{"ID":7751,"Offset":68880,"Name":"黄杏种子","Description":null},{"ID":7752,"Offset":69104,"Name":"拉诺西亚韭菜种子","Description":null},{"ID":7753,"Offset":69364,"Name":"提诺尔卡茶树种子","Description":null},{"ID":7754,"Offset":69624,"Name":"伞叶无花果种子","Description":null},{"ID":7755,"Offset":69872,"Name":"黄麻种子","Description":null},{"ID":7756,"Offset":70096,"Name":"釉质坚果种子","Description":null},{"ID":7757,"Offset":70336,"Name":"扫帚草种子","Description":null},{"ID":7758,"Offset":70568,"Name":"1级拉诺西亚土壤","Description":null},{"ID":7759,"Offset":70876,"Name":"2级拉诺西亚土壤","Description":null},{"ID":7760,"Offset":71184,"Name":"3级拉诺西亚土壤","Description":null},{"ID":7761,"Offset":71492,"Name":"1级黑衣森林土壤","Description":null},{"ID":7762,"Offset":71800,"Name":"2级黑衣森林土壤","Description":null},{"ID":7763,"Offset":72108,"Name":"3级黑衣森林土壤","Description":null},{"ID":7764,"Offset":72416,"Name":"1级萨纳兰土壤","Description":null},{"ID":7765,"Offset":72712,"Name":"2级萨纳兰土壤","Description":null},{"ID":7766,"Offset":73008,"Name":"3级萨纳兰土壤","Description":null},{"ID":7767,"Offset":73304,"Name":"鱼粉","Description":null},{"ID":7768,"Offset":73564,"Name":"哈罗妮丁菊","Description":null},{"ID":7769,"Offset":73824,"Name":"阿泽玛玫瑰","Description":null},{"ID":7770,"Offset":74084,"Name":"妮美雅百合","Description":null},{"ID":7771,"Offset":74344,"Name":"礼服面料","Description":null},{"ID":7772,"Offset":74600,"Name":"耐水棉布","Description":null},{"ID":7773,"Offset":74856,"Name":"伞叶无花果","Description":null},{"ID":7774,"Offset":75160,"Name":"黄麻","Description":null},{"ID":7775,"Offset":75404,"Name":"釉质坚果","Description":null},{"ID":7776,"Offset":75664,"Name":"扫帚草","Description":null},{"ID":7777,"Offset":75928,"Name":"黄麻线","Description":null},{"ID":7778,"Offset":76152,"Name":"木工秘籍第一卷","Description":null},{"ID":7779,"Offset":76488,"Name":"锻冶秘籍第一卷","Description":null},{"ID":7780,"Offset":76824,"Name":"甲胄秘籍第一卷","Description":null},{"ID":7781,"Offset":77160,"Name":"雕金秘籍第一卷","Description":null},{"ID":7782,"Offset":77496,"Name":"皮革秘籍第一卷","Description":null},{"ID":7783,"Offset":77832,"Name":"裁缝秘籍第一卷","Description":null},{"ID":7784,"Offset":78168,"Name":"炼金秘籍第一卷","Description":null},{"ID":7785,"Offset":78512,"Name":"烹调秘籍第一卷","Description":null},{"ID":7786,"Offset":78848,"Name":"木工秘籍幻象之卷","Description":null},{"ID":7787,"Offset":79192,"Name":"锻冶秘籍幻象之卷","Description":null},{"ID":7788,"Offset":79536,"Name":"甲胄秘籍幻象之卷","Description":null},{"ID":7789,"Offset":79880,"Name":"雕金秘籍幻象之卷","Description":null},{"ID":7790,"Offset":80224,"Name":"皮革秘籍幻象之卷","Description":null},{"ID":7791,"Offset":80568,"Name":"裁缝秘籍幻象之卷","Description":null},{"ID":7792,"Offset":80912,"Name":"炼金秘籍幻象之卷","Description":null},{"ID":7793,"Offset":81260,"Name":"","Description":null},{"ID":7794,"Offset":81432,"Name":"轻钢板","Description":null},{"ID":7795,"Offset":81648,"Name":"平纹布","Description":null},{"ID":7796,"Offset":81896,"Name":"探险币","Description":null},{"ID":7797,"Offset":82168,"Name":"秘银大锤币","Description":null},{"ID":7798,"Offset":82428,"Name":"珊瑚手镯","Description":null},{"ID":7799,"Offset":82688,"Name":"里根圆椒","Description":null},{"ID":7800,"Offset":83032,"Name":"","Description":null},{"ID":7801,"Offset":83204,"Name":"","Description":null},{"ID":7802,"Offset":83376,"Name":"白钢大锤币","Description":null},{"ID":7803,"Offset":83636,"Name":"绿金大锤币","Description":null},{"ID":7804,"Offset":83896,"Name":"珊瑚指环","Description":null},{"ID":7805,"Offset":84156,"Name":"珊瑚项链","Description":null},{"ID":7806,"Offset":84428,"Name":"黄褐乳胶","Description":null},{"ID":7807,"Offset":84688,"Name":"终结油灰","Description":null},{"ID":7808,"Offset":84988,"Name":"庄园清漆","Description":null},{"ID":7809,"Offset":85252,"Name":"魔法棱晶（日光）","Description":null},{"ID":7810,"Offset":85572,"Name":"魔法棱晶（星尘）","Description":null},{"ID":7811,"Offset":85892,"Name":"罗薇娜的战记票据","Description":null},{"ID":7812,"Offset":86188,"Name":"未鉴定的亚拉戈神典石","Description":null},{"ID":7813,"Offset":86520,"Name":"渊水长刀","Description":null},{"ID":7814,"Offset":86716,"Name":"渊水拳剑","Description":null},{"ID":7815,"Offset":86912,"Name":"渊水长刃斧","Description":null},{"ID":7816,"Offset":87112,"Name":"渊水渔枪","Description":null},{"ID":7817,"Offset":87308,"Name":"渊水长弓","Description":null},{"ID":7818,"Offset":87504,"Name":"渊水幻杖","Description":null},{"ID":7819,"Offset":87700,"Name":"渊水长杖","Description":null},{"ID":7820,"Offset":87896,"Name":"渊水魔书","Description":null},{"ID":7821,"Offset":88092,"Name":"渊水魔典","Description":null},{"ID":7822,"Offset":88288,"Name":"渊水坚盾","Description":null},{"ID":7823,"Offset":88484,"Name":"渊水圆盾","Description":null},{"ID":7824,"Offset":88680,"Name":"无锋剑柯塔纳·魂晶","Description":null},{"ID":7825,"Offset":88904,"Name":"释法来·魂晶","Description":null},{"ID":7826,"Offset":89108,"Name":"勇悍斧·魂晶","Description":null},{"ID":7827,"Offset":89312,"Name":"穿心枪盖博尔格·魂晶","Description":null},{"ID":7828,"Offset":89540,"Name":"月神之弓·魂晶","Description":null},{"ID":7829,"Offset":89752,"Name":"酒神杖·魂晶","Description":null},{"ID":7830,"Offset":89956,"Name":"星尘杖·魂晶","Description":null},{"ID":7831,"Offset":90160,"Name":"绿瞳列传·魂晶","Description":null},{"ID":7832,"Offset":90372,"Name":"万辞全书·魂晶","Description":null},{"ID":7833,"Offset":90584,"Name":"神圣盾·魂晶","Description":null},{"ID":7834,"Offset":90788,"Name":"无锋剑柯塔纳·魂灵","Description":null},{"ID":7835,"Offset":91012,"Name":"释法来·魂灵","Description":null},{"ID":7836,"Offset":91216,"Name":"勇悍斧·魂灵","Description":null},{"ID":7837,"Offset":91420,"Name":"穿心枪盖博尔格·魂灵","Description":null},{"ID":7838,"Offset":91648,"Name":"月神之弓·魂灵","Description":null},{"ID":7839,"Offset":91860,"Name":"酒神杖·魂灵","Description":null},{"ID":7840,"Offset":92064,"Name":"星尘杖·魂灵","Description":null},{"ID":7841,"Offset":92268,"Name":"绿瞳列传·魂灵","Description":null},{"ID":7842,"Offset":92480,"Name":"万辞全书·魂灵","Description":null},{"ID":7843,"Offset":92692,"Name":"神圣盾·魂灵","Description":null},{"ID":7844,"Offset":92896,"Name":"火妖笛","Description":null},{"ID":7845,"Offset":93148,"Name":"风妖笛","Description":null},{"ID":7846,"Offset":93400,"Name":"土妖笛","Description":null},{"ID":7847,"Offset":93656,"Name":"水妖笛","Description":null},{"ID":7848,"Offset":93908,"Name":"战狮角笛","Description":null},{"ID":7849,"Offset":94148,"Name":"战熊角笛","Description":null},{"ID":7850,"Offset":94388,"Name":"水神魔镜","Description":null},{"ID":7851,"Offset":94636,"Name":"室女之魂晶","Description":null},{"ID":7852,"Offset":94884,"Name":"天蝎之魂晶","Description":null},{"ID":7853,"Offset":95132,"Name":"宝瓶之魂晶","Description":null},{"ID":7854,"Offset":95388,"Name":"摩羯之魂晶","Description":null},{"ID":7855,"Offset":95636,"Name":"金牛之魂晶","Description":null},{"ID":7856,"Offset":95884,"Name":"白羊之魂晶","Description":null},{"ID":7857,"Offset":96136,"Name":"双子之魂晶","Description":null},{"ID":7858,"Offset":96384,"Name":"狮子之魂晶","Description":null},{"ID":7859,"Offset":96640,"Name":"双鱼之魂晶","Description":null},{"ID":7860,"Offset":96896,"Name":"人马之魂晶","Description":null},{"ID":7861,"Offset":97144,"Name":"天秤之魂晶","Description":null},{"ID":7862,"Offset":97392,"Name":"巨蟹之魂晶","Description":null},{"ID":7863,"Offset":97644,"Name":"无锋剑柯塔纳·新星","Description":null},{"ID":7864,"Offset":97868,"Name":"释法来·新星","Description":null},{"ID":7865,"Offset":98072,"Name":"勇悍斧·新星","Description":null},{"ID":7866,"Offset":98276,"Name":"穿心枪盖博尔格·新星","Description":null},{"ID":7867,"Offset":98504,"Name":"月神之弓·新星","Description":null},{"ID":7868,"Offset":98716,"Name":"酒神杖·新星","Description":null},{"ID":7869,"Offset":98920,"Name":"星尘杖·新星","Description":null},{"ID":7870,"Offset":99124,"Name":"绿瞳列传·新星","Description":null},{"ID":7871,"Offset":99336,"Name":"万辞全书·新星","Description":null},{"ID":7872,"Offset":99548,"Name":"神圣盾·新星","Description":null},{"ID":7873,"Offset":99752,"Name":"圣剑天球书卷","Description":null},{"ID":7874,"Offset":100008,"Name":"双豹天球书卷","Description":null},{"ID":7875,"Offset":100256,"Name":"战斧天球书卷","Description":null},{"ID":7876,"Offset":100504,"Name":"龙枪天球书卷","Description":null},{"ID":7877,"Offset":100764,"Name":"神弓天球书卷","Description":null},{"ID":7878,"Offset":101012,"Name":"灵杖天球书卷","Description":null},{"ID":7879,"Offset":101260,"Name":"星杖天球书卷","Description":null},{"ID":7880,"Offset":101508,"Name":"魔书天球书卷","Description":null},{"ID":7881,"Offset":101756,"Name":"奇书天球书卷","Description":null},{"ID":7882,"Offset":102004,"Name":"圣盾天球书卷","Description":null},{"ID":7883,"Offset":102252,"Name":"星光变石","Description":null},{"ID":7884,"Offset":102504,"Name":"神秘地图","Description":null},{"ID":7885,"Offset":102860,"Name":"高位附魔墨水","Description":null},{"ID":7886,"Offset":103140,"Name":"","Description":null},{"ID":7887,"Offset":103312,"Name":"","Description":null},{"ID":7888,"Offset":103484,"Name":"","Description":null},{"ID":7889,"Offset":103656,"Name":"","Description":null},{"ID":7890,"Offset":103828,"Name":"","Description":null},{"ID":7891,"Offset":104000,"Name":"","Description":null},{"ID":7892,"Offset":104172,"Name":"","Description":null},{"ID":7893,"Offset":104344,"Name":"","Description":null},{"ID":7894,"Offset":104516,"Name":"库里尔萝卜","Description":null},{"ID":7895,"Offset":104876,"Name":"希尔奇斯菜蓟","Description":null},{"ID":7896,"Offset":105224,"Name":"","Description":null},{"ID":7897,"Offset":105396,"Name":"米梅特葫芦","Description":null},{"ID":7898,"Offset":105756,"Name":"坦塔尔矮瓜","Description":null},{"ID":7899,"Offset":106104,"Name":"","Description":null},{"ID":7900,"Offset":106276,"Name":"帕萨纳红茄","Description":null},{"ID":7901,"Offset":106636,"Name":"怪物猎人的手册","Description":null},{"ID":7902,"Offset":106936,"Name":"鱼大叔","Description":null},{"ID":7903,"Offset":107236,"Name":"陨石幸存者","Description":null},{"ID":7904,"Offset":107488,"Name":"圣鳟贞德","Description":null},{"ID":7905,"Offset":107736,"Name":"特拉玛豹鱼","Description":null},{"ID":7906,"Offset":107984,"Name":"断指龙虾","Description":null},{"ID":7907,"Offset":108232,"Name":"终结者","Description":null},{"ID":7908,"Offset":108476,"Name":"大蛇鳗","Description":null},{"ID":7909,"Offset":108720,"Name":"比阿纳可大帝","Description":null},{"ID":7910,"Offset":108988,"Name":"肮脏鲱","Description":null},{"ID":7911,"Offset":109248,"Name":"虚空之眼","Description":null},{"ID":7912,"Offset":109496,"Name":"妖祸鱼","Description":null},{"ID":7913,"Offset":109736,"Name":"浮游石","Description":null},{"ID":7914,"Offset":109988,"Name":"露齿鲤","Description":null},{"ID":7915,"Offset":110248,"Name":"金枪鲨","Description":null},{"ID":7916,"Offset":110496,"Name":"尼姆蠕虫","Description":null},{"ID":7917,"Offset":110748,"Name":"抽须王","Description":null},{"ID":7918,"Offset":111048,"Name":"太阳神杖","Description":null},{"ID":7919,"Offset":111308,"Name":"枪鼻头","Description":null},{"ID":7920,"Offset":111588,"Name":"雷神光","Description":null},{"ID":7921,"Offset":111832,"Name":"沉川鲑","Description":null},{"ID":7922,"Offset":112104,"Name":"刺鱼教父","Description":null},{"ID":7923,"Offset":112360,"Name":"芳香蝾螈","Description":null},{"ID":7924,"Offset":112684,"Name":"轰击泡","Description":null},{"ID":7925,"Offset":112948,"Name":"浓盐鲀","Description":null},{"ID":7926,"Offset":113212,"Name":"孤独杀手","Description":null},{"ID":7927,"Offset":113480,"Name":"温泉王","Description":null},{"ID":7928,"Offset":113748,"Name":"铁饼","Description":null},{"ID":7929,"Offset":114012,"Name":"铁索","Description":null},{"ID":7930,"Offset":114264,"Name":"沙海肠虫","Description":null},{"ID":7931,"Offset":114548,"Name":"魔毯","Description":null},{"ID":7932,"Offset":114804,"Name":"圣人标","Description":null},{"ID":7933,"Offset":115064,"Name":"冥河灯","Description":null},{"ID":7934,"Offset":115328,"Name":"绿小丑","Description":null},{"ID":7935,"Offset":115592,"Name":"血浴","Description":null},{"ID":7936,"Offset":115856,"Name":"雷皇子","Description":null},{"ID":7937,"Offset":116120,"Name":"吞雷鱼","Description":null},{"ID":7938,"Offset":116384,"Name":"沉溺射手","Description":null},{"ID":7939,"Offset":116652,"Name":"丽舞蟹","Description":null},{"ID":7940,"Offset":116916,"Name":"银镜鱼","Description":null},{"ID":7941,"Offset":117176,"Name":"翻舵手","Description":null},{"ID":7942,"Offset":117440,"Name":"千年殇","Description":null},{"ID":7943,"Offset":117704,"Name":"汉尼拔","Description":null},{"ID":7944,"Offset":117968,"Name":"黎明少女","Description":null},{"ID":7945,"Offset":118236,"Name":"星光鳟鱼","Description":null},{"ID":7946,"Offset":118508,"Name":"一家之母","Description":null},{"ID":7947,"Offset":118788,"Name":"影纹狗鱼","Description":null},{"ID":7948,"Offset":119060,"Name":"船长圣杯","Description":null},{"ID":7949,"Offset":119328,"Name":"奇虾","Description":null},{"ID":7950,"Offset":119584,"Name":"皱鳃鲨","Description":null},{"ID":7951,"Offset":119884,"Name":"以太虱","Description":null},{"ID":7952,"Offset":120184,"Name":"","Description":null},{"ID":7953,"Offset":120356,"Name":"","Description":null},{"ID":7954,"Offset":120528,"Name":"","Description":null},{"ID":7955,"Offset":120700,"Name":"","Description":null},{"ID":7956,"Offset":120872,"Name":"","Description":null},{"ID":7957,"Offset":121044,"Name":"","Description":null},{"ID":7958,"Offset":121216,"Name":"海滨墙架","Description":null},{"ID":7959,"Offset":121440,"Name":"","Description":null},{"ID":7960,"Offset":121612,"Name":"","Description":null},{"ID":7961,"Offset":121784,"Name":"","Description":null},{"ID":7962,"Offset":121956,"Name":"","Description":null},{"ID":7963,"Offset":122128,"Name":"","Description":null},{"ID":7964,"Offset":122300,"Name":"«五纪历»","Description":null},{"ID":7965,"Offset":122732,"Name":"机密文件","Description":null},{"ID":7966,"Offset":123000,"Name":"毛绒绒哥布林","Description":null},{"ID":7967,"Offset":123316,"Name":"小型究极神兵","Description":null},{"ID":7968,"Offset":123608,"Name":"","Description":null},{"ID":7969,"Offset":123780,"Name":"调查员与助手的肖像画","Description":null},{"ID":7970,"Offset":124112,"Name":"墙上盆栽","Description":null},{"ID":7971,"Offset":124356,"Name":"«艾欧泽亚百科全书»","Description":null},{"ID":7972,"Offset":124820,"Name":"开放式火炉","Description":null},{"ID":7973,"Offset":125144,"Name":"海滨隔离矮墙","Description":null},{"ID":7974,"Offset":125452,"Name":"伞叶无花果盆栽","Description":null},{"ID":7975,"Offset":125740,"Name":"龙血树盆栽","Description":null},{"ID":7976,"Offset":126124,"Name":"天球仪","Description":null},{"ID":7977,"Offset":126420,"Name":"榻榻米","Description":null},{"ID":7978,"Offset":126660,"Name":"转角柜台","Description":null},{"ID":7979,"Offset":126884,"Name":"植物隔离矮墙","Description":null},{"ID":7980,"Offset":127124,"Name":"拉姆等离子灯","Description":null},{"ID":7981,"Offset":127464,"Name":"雷神等离子灯","Description":null},{"ID":7982,"Offset":127804,"Name":"始皇宝座","Description":null},{"ID":7983,"Offset":128140,"Name":"海滨门垫","Description":null},{"ID":7984,"Offset":128364,"Name":"双人羽床","Description":null},{"ID":7985,"Offset":128624,"Name":"陆行鸟立柱","Description":null},{"ID":7986,"Offset":128864,"Name":"海滨软垫","Description":null},{"ID":7987,"Offset":129088,"Name":"林间软垫","Description":null},{"ID":7988,"Offset":129312,"Name":"绿洲软垫","Description":null},{"ID":7989,"Offset":129536,"Name":"陆行鸟房","Description":null},{"ID":7990,"Offset":129856,"Name":"红莲灯笼","Description":null},{"ID":7991,"Offset":130096,"Name":"东方的许愿竹","Description":null},{"ID":7992,"Offset":130416,"Name":"球形灌木","Description":null},{"ID":7993,"Offset":130652,"Name":"格子盆栽","Description":null},{"ID":7994,"Offset":130916,"Name":"睡莲水盆","Description":null},{"ID":7995,"Offset":131168,"Name":"庭院水塘","Description":null},{"ID":7996,"Offset":131404,"Name":"吊锅","Description":null},{"ID":7997,"Offset":131644,"Name":"活梯","Description":null},{"ID":7998,"Offset":131884,"Name":"直线踏脚石","Description":null},{"ID":7999,"Offset":132112,"Name":"弧形踏脚石","Description":null}]